mindful/__init__.py
mindful/__main__.py
mindful/api.py
mindful/board.py
mindful/cli.py
mindful/configs.py
mindful/defaults.py
mindful/times.py
mindful-0.0.0.dist-info/entry_points.txt
mindful-0.0.0.dist-info/LICENSE
mindful-0.0.0.dist-info/WHEEL
mindful-0.0.0.dist-info/METADATA
mindful-0.0.0.dist-info/RECORD
