Metadata-Version: 2.1
Name: mindful
Version: 0.0.0
Summary: Utilities for analyzing Trello boards.
Author-email: blakeNaccarato <blake.naccarato+mindful@gmail.com>
Requires-Python: >=3.11
Requires-Dist: datamodel-code-generator~=0.14.0
Requires-Dist: pyperclip~=1.8.2
Requires-Dist: typer~=0.7.0
Project-URL: Home, https://github.com/blakeNaccarato/mindful
